[
    {
        "_id": 99,
        "name": "Zhong Li",
        "Qualification":[
            "Medical practioner",
             "Root Canal Specialist"
        ],
        "clinic_id": [
            "1",
            "3"
        ],
        "patient_id": [
            "100022",
            "987123"
        ]
    },
    
    {
        "_id": 90,
        "name": "Eric Zhou",
        "Qualification":[
            "Doctor of Dental Surgery (DDS)",
             "Bachelor of Dental Surgery (BDS)"
        ],
        "clinic_id": 3,
        "appointment_id": 100022
    },
    {
        "_id": 18,
        "name": "Eric Zhou",
        "Qualification":[
            "Doctor of Dental Surgery (DDS)",
             "Bachelor of Dental Surgery (BDS)"
        ],
        "clinic_id": 3,
        "appointment_id": 100022
    },
    {
        "_id": 88,
        "name": "Eric Zhou",
        "Qualification":[
            "Doctor of Dental Surgery (DDS)",
             "Bachelor of Dental Surgery (BDS)"
        ],
        "clinic_id": 3,
        "appointment_id": 100022
    }
]